MANIFEST.in
README.txt
setup.py
docs/HISTORY.txt
docs/INSTALL.txt
docs/LICENSE.GPL
docs/LICENSE.txt
quintagroup/__init__.py
quintagroup.z3cform.captcha.egg-info/PKG-INFO
quintagroup.z3cform.captcha.egg-info/SOURCES.txt
quintagroup.z3cform.captcha.egg-info/dependency_links.txt
quintagroup.z3cform.captcha.egg-info/entry_points.txt
quintagroup.z3cform.captcha.egg-info/namespace_packages.txt
quintagroup.z3cform.captcha.egg-info/not-zip-safe
quintagroup.z3cform.captcha.egg-info/requires.txt
quintagroup.z3cform.captcha.egg-info/top_level.txt
quintagroup/z3cform/__init__.py
quintagroup/z3cform/captcha/__init__.py
quintagroup/z3cform/captcha/configure.zcml
quintagroup/z3cform/captcha/error.py
quintagroup/z3cform/captcha/field.py
quintagroup/z3cform/captcha/interfaces.py
quintagroup/z3cform/captcha/meta.zcml
quintagroup/z3cform/captcha/tests.py
quintagroup/z3cform/captcha/validator.py
quintagroup/z3cform/captcha/widget.py