Metadata-Version: 1.0
Name: quintagroup.z3cform.captcha
Version: 1.0.3
Summary: Captcha field for z3cform based on quintagroup.captcha.core package
Home-page: http://svn.quintagroup.com/products/quintagroup.z3cform.captcha/
Author: Quintagroup
Author-email: support@quintagroup.com
License: GPL
Keywords: plone z3c form captcha
Platform: UNKNOWN
Classifier: Development Status :: 5 - Production/Stable
Classifier: Environment :: Web Environment
Classifier: Framework :: Plone
Classifier: Framework :: Plone :: 3.2
Classifier: Framework :: Plone :: 3.3
Classifier: Framework :: Plone :: 4.0
Classifier: Framework :: Plone :: 4.1
Classifier: Framework :: Plone :: 4.2
Classifier: Framework :: Plone :: 4.3
Classifier: Framework :: Zope2
Classifier: Framework :: Zope3
Classifier: License :: OSI Approved :: GNU General Public License (GPL)
Classifier: Operating System :: OS Independent
Classifier: Programming Language :: Python
Classifier: Topic :: Security
Classifier: Topic :: Software Development :: Libraries :: Python Modules
